litex.novitus-1.0.0-py3.8-nspkg.pth
litex/novitus/__init__.py
litex/novitus/exceptions.py
litex/novitus/helpers.py
litex/novitus/printer.py
litex.novitus-1.0.0.dist-info/LICENSE
litex.novitus-1.0.0.dist-info/METADATA
litex.novitus-1.0.0.dist-info/WHEEL
litex.novitus-1.0.0.dist-info/namespace_packages.txt
litex.novitus-1.0.0.dist-info/top_level.txt
litex.novitus-1.0.0.dist-info/RECORD
