Metadata-Version: 2.1
Name: litex.novitus
Version: 1.0.0
Summary: A Novitus Protocol Fiscal Printer Library
Home-page: UNKNOWN
Author: Michał Węgrzynek
Author-email: mwegrzynek@litexservice.pl
License: UNKNOWN
Platform: UNKNOWN
Requires-Dist: pyserial
